valuesets/__init__.py
valuesets/_version.py
valuesets/cli.py
valuesets/datamodel/valuesets.py
valuesets/datamodel/valuesets_dataclass.py
valuesets/datamodel/valuesets_pydantic.py
valuesets/enums/__init__.py
valuesets/enums/common_value_sets.py
valuesets/enums/confidence_levels.py
valuesets/enums/contributor.py
valuesets/enums/core.py
valuesets/enums/demographics.py
valuesets/enums/ecological_interactions.py
valuesets/enums/health.py
valuesets/enums/health_base.py
valuesets/enums/healthcare.py
valuesets/enums/investigation.py
valuesets/enums/mining_processing.py
valuesets/enums/statistics.py
valuesets/enums/stewardship.py
valuesets/enums/academic/__init__.py
valuesets/enums/academic/organizations.py
valuesets/enums/academic/research.py
valuesets/enums/analytical_chemistry/__init__.py
valuesets/enums/analytical_chemistry/mass_spectrometry.py
valuesets/enums/bio/__init__.py
valuesets/enums/bio/assays.py
valuesets/enums/bio/bgc_categories.py
valuesets/enums/bio/biological_colors.py
valuesets/enums/bio/biosafety.py
valuesets/enums/bio/cell_cycle.py
valuesets/enums/bio/currency_chemicals.py
valuesets/enums/bio/developmental_stages.py
valuesets/enums/bio/expression_units.py
valuesets/enums/bio/gene_perturbation.py
valuesets/enums/bio/genome_features.py
valuesets/enums/bio/genomics.py
valuesets/enums/bio/go_aspect.py
valuesets/enums/bio/go_causality.py
valuesets/enums/bio/go_evidence.py
valuesets/enums/bio/human_developmental_stages.py
valuesets/enums/bio/insdc_geographic_locations.py
valuesets/enums/bio/insdc_missing_values.py
valuesets/enums/bio/lipid_categories.py
valuesets/enums/bio/mouse_developmental_stages.py
valuesets/enums/bio/plant_biology.py
valuesets/enums/bio/plant_developmental_stages.py
valuesets/enums/bio/plant_experimental_conditions.py
valuesets/enums/bio/plant_sex.py
valuesets/enums/bio/protein_evidence.py
valuesets/enums/bio/proteomics_standards.py
valuesets/enums/bio/psi_mi.py
valuesets/enums/bio/relationship_to_oxygen.py
valuesets-0.4.2.dist-info/METADATA
valuesets-0.4.2.dist-info/WHEEL
valuesets-0.4.2.dist-info/entry_points.txt
valuesets-0.4.2.dist-info/licenses/LICENSE
valuesets-0.4.2.dist-info/RECORD
