Metadata-Version: 2.4
Name: valuesets
Version: 0.4.2
Summary: A collection of commonly used value sets
Author-email: Chris Mungall <cjmungall@lbl.gov>
License-Expression: Apache-2.0
License-File: LICENSE
Requires-Python: <4.0,>=3.10
Requires-Dist: linkml-runtime>=1.9.4
Requires-Dist: oaklib>=0.6.23
Requires-Dist: ruamel-yaml>=0.18.15
Requires-Dist: typer>=0.20.0
